MLedu-0.0.2.2.dist-info/DESCRIPTION.rst
MLedu-0.0.2.2.dist-info/METADATA
MLedu-0.0.2.2.dist-info/RECORD
MLedu-0.0.2.2.dist-info/WHEEL
MLedu-0.0.2.2.dist-info/entry_points.txt
MLedu-0.0.2.2.dist-info/metadata.json
MLedu-0.0.2.2.dist-info/top_level.txt
src/__init__.py
src/base.py
src/jupyter.py
src/norms.py
src/ori_regression.py
src/regression.py
src/utils.py
