Metadata-Version: 2.0
Name: MLedu
Version: 0.0.2.2
Summary: build machine learning models for education purpose
Home-page: https://github.com/shichaoji/MLedu
Author: Shichao(Richard) Ji
Author-email: jshichao@vt.edu
License: MIT
Download-URL: https://github.com/shichaoji/MLedu/archive/0.1.tar.gz
Keywords: data science,data mining,text mining,natual language processing
Platform: UNKNOWN
Classifier: License :: OSI Approved :: MIT License
Classifier: Programming Language :: Python :: 2
Requires-Dist: numpy
